setup.py
python_shovel/__init__.py
python_shovel/api_client.py
python_shovel/configuration.py
python_shovel/rest.py
python_shovel.egg-info/PKG-INFO
python_shovel.egg-info/SOURCES.txt
python_shovel.egg-info/dependency_links.txt
python_shovel.egg-info/requires.txt
python_shovel.egg-info/top_level.txt
python_shovel/apis/__init__.py
python_shovel/apis/del_api.py
python_shovel/apis/get_api.py
python_shovel/apis/patch_api.py
python_shovel/apis/post_api.py
python_shovel/models/__init__.py
python_shovel/models/config.py
python_shovel/models/glance.py
python_shovel/models/ironic.py
python_shovel/models/keystone.py
python_shovel/models/monorail.py
python_shovel/models/patchnode.py
python_shovel/models/patchnode_inner.py
python_shovel/models/regnode.py