Metadata-Version: 1.0
Name: python-shovel
Version: 1.0.0
Summary: Shovel APIs
Home-page: UNKNOWN
Author: UNKNOWN
Author-email: UNKNOWN
License: UNKNOWN
Keywords: Swagger,Shovel APIs
Platform: UNKNOWN
